dcb_admin_page_generator/__init__.py
dcb_admin_page_generator/common_class.py
dcb_admin_page_generator/config.py
dcb_admin_page_generator/funcs.py
dcb_admin_page_generator/main.py
dcb_admin_page_generator/page_class.py
dcb_admin_page_generator/template/__init__.py
dcb_admin_page_generator/template/add_or_edit.vue
dcb_admin_page_generator/template/dialog_add_or_edit.vue
dcb_admin_page_generator/template/dialog_list.vue
dcb_admin_page_generator/template/list.vue
dcb_admin_page_generator/template/list_v2.vue
dcb_admin_page_generator-0.0.8.dist-info/LICENSE
dcb_admin_page_generator-0.0.8.dist-info/METADATA
dcb_admin_page_generator-0.0.8.dist-info/WHEEL
dcb_admin_page_generator-0.0.8.dist-info/top_level.txt
dcb_admin_page_generator-0.0.8.dist-info/RECORD
