Metadata-Version: 2.1
Name: dcb_admin_page_generator
Version: 0.0.8
Summary: A small example package
Home-page: https://github.com/pypa/sampleproject
Author: wyz
Author-email: 846630116@qq.com
Classifier: Programming Language :: Python :: 3
Classifier: License :: OSI Approved :: MIT License
Classifier: Operating System :: OS Independent
License-File: LICENSE
